slugify/__init__.py
slugify/__main__.py
slugify/__version__.py
slugify/py.typed
slugify/slugify.py
slugify/special.py
python_slugify-8.0.3.dist-info/LICENSE
python_slugify-8.0.3.dist-info/METADATA
python_slugify-8.0.3.dist-info/WHEEL
python_slugify-8.0.3.dist-info/entry_points.txt
python_slugify-8.0.3.dist-info/top_level.txt
python_slugify-8.0.3.dist-info/RECORD
